[
  {"state":"Alabama","status":"unknown","last_confirmed":null,"source":""},
  {"state":"Alaska","status":"unknown","last_confirmed":null,"source":""},
  {"state":"Arizona","status":"unknown","last_confirmed":null,"source":""},
  {"state":"Arkansas","status":"unknown","last_confirmed":null,"source":""},
  {"state":"California","status":"unknown","last_confirmed":null,"source":""},
  {"state":"Colorado","status":"unknown","last_confirmed":null,"source":""},
  {"state":"Connecticut","status":"unknown","last_confirmed":null,"source":""},
  {"state":"Delaware","status":"unknown","last_confirmed":null,"source":""},
  {"state":"District of Columbia","status":"unknown","last_confirmed":null,"source":""},
  {"state":"Florida","status":"unknown","last_confirmed":null,"source":""},
  {"state":"Georgia","status":"unknown","last_confirmed":null,"source":""},
  {"state":"Guam","status":"unknown","last_confirmed":null,"source":""},
  {"state":"Hawaii","status":"unknown","last_confirmed":null,"source":""},
  {"state":"Idaho","status":"unknown","last_confirmed":null,"source":""},
  {"state":"Illinois","status":"unknown","last_confirmed":null,"source":""},
  {"state":"Indiana","status":"unknown","last_confirmed":null,"source":""},
  {"state":"Iowa","status":"unknown","last_confirmed":null,"source":""},
  {"state":"Kansas","status":"unknown","last_confirmed":null,"source":""},
  {"state":"Kentucky","status":"unknown","last_confirmed":null,"source":""},
  {"state":"Louisiana","status":"unknown","last_confirmed":null,"source":""},
  {"state":"Maine","status":"unknown","last_confirmed":null,"source":""},
  {"state":"Maryland","status":"unknown","last_confirmed":null,"source":""},
  {"state":"Massachusetts","status":"unknown","last_confirmed":null,"source":""},
  {"state":"Michigan","status":"unknown","last_confirmed":null,"source":""},
  {"state":"Minnesota","status":"unknown","last_confirmed":null,"source":""},
  {"state":"Mississippi","status":"unknown","last_confirmed":null,"source":""},
  {"state":"Missouri","status":"unknown","last_confirmed":null,"source":""},
  {"state":"Montana","status":"unknown","last_confirmed":null,"source":""},
  {"state":"Nebraska","status":"unknown","last_confirmed":null,"source":""},
  {"state":"Nevada","status":"unknown","last_confirmed":null,"source":""},
  {"state":"New Hampshire","status":"unknown","last_confirmed":null,"source":""},
  {"state":"New Jersey","status":"unknown","last_confirmed":null,"source":""},
  {"state":"New Mexico","status":"unknown","last_confirmed":null,"source":""},
  {"state":"New York","status":"unknown","last_confirmed":null,"source":""},
  {"state":"North Carolina","status":"unknown","last_confirmed":null,"source":""},
  {"state":"North Dakota","status":"unknown","last_confirmed":null,"source":""},
  {"state":"Ohio","status":"unknown","last_confirmed":null,"source":""},
  {"state":"Oklahoma","status":"unknown","last_confirmed":null,"source":""},
  {"state":"Oregon","status":"unknown","last_confirmed":null,"source":""},
  {"state":"Pennsylvania","status":"unknown","last_confirmed":null,"source":""},
  {"state":"Rhode Island","status":"unknown","last_confirmed":null,"source":""},
  {"state":"South Carolina","status":"unknown","last_confirmed":null,"source":""},
  {"state":"South Dakota","status":"unknown","last_confirmed":null,"source":""},
  {"state":"Tennessee","status":"unknown","last_confirmed":null,"source":""},
  {"state":"Texas","status":"unknown","last_confirmed":null,"source":""},
  {"state":"Utah","status":"unknown","last_confirmed":null,"source":""},
  {"state":"Vermont","status":"unknown","last_confirmed":null,"source":""},
  {"state":"Virginia","status":"unknown","last_confirmed":null,"source":""},
  {"state":"Virgin Islands","status":"unknown","last_confirmed":null,"source":""},
  {"state":"Washington","status":"unknown","last_confirmed":null,"source":""},
  {"state":"West Virginia","status":"unknown","last_confirmed":null,"source":""},
  {"state":"Wisconsin","status":"unknown","last_confirmed":null,"source":""},
  {"state":"Wyoming","status":"unknown","last_confirmed":null,"source":""}
]
